aiofsm/__init__.py
aiofsm/__version__.py
aiofsm-0.1.0a1.dist-info/METADATA
aiofsm-0.1.0a1.dist-info/WHEEL
aiofsm-0.1.0a1.dist-info/RECORD
