Metadata-Version: 2.4
Name: aiofsm
Version: 0.1.0a1
Summary: Lightweight async finite state machine with hierarchical states.
License: MIT
Requires-Python: >=3.8
